linguin/__init__.py
linguin/exceptions.py
linguin/linguin.py
linguin/linguin_response.py
linguin-2.0.0.dist-info/LICENSE
linguin-2.0.0.dist-info/METADATA
linguin-2.0.0.dist-info/WHEEL
linguin-2.0.0.dist-info/top_level.txt
linguin-2.0.0.dist-info/RECORD
