Metadata-Version: 2.1
Name: linguin
Version: 2.0.0
Summary: API wrapper for the language detection as a service Linguin AI.
Home-page: https://linguin.ai/
Author: Jan Schwenzien
Author-email: jan@general-scripting.com
License: UNKNOWN
Project-URL: Bug Tracker, https://github.com/LinguinAI/linguin-python/issues
Project-URL: Documentation, https://linguin.ai/api-docs/v2/
Platform: UNKNOWN
Classifier: Programming Language :: Python :: 3
Classifier: License :: OSI Approved :: MIT License
Classifier: Operating System :: OS Independent
Requires-Python: >=3.6
License-File: LICENSE
Requires-Dist: requests
